textual_game_of_life/__init__.py
textual_game_of_life/__main__.py
textual_game_of_life/canvas.py
textual_game_of_life/modals.py
textual_game_of_life/tui.py
textual_game_of_life-1.2.0.dist-info/licenses/LICENSE
textual_game_of_life-1.2.0.dist-info/METADATA
textual_game_of_life-1.2.0.dist-info/WHEEL
textual_game_of_life-1.2.0.dist-info/entry_points.txt
textual_game_of_life-1.2.0.dist-info/top_level.txt
textual_game_of_life-1.2.0.dist-info/RECORD
