Metadata-Version: 2.4
Name: textual-game-of-life
Version: 1.2.0
Summary: An implementation of Conway's game of life (cellular automata) in the terminal using textual.
Author-email: Thomas Crha <thomas@9bitbyte.com>
Project-URL: Homepage, https://github.com/thomascrha/textual-game-of-life
Project-URL: Bug Tracker, https://github.com/thomascrha/textual-game-of-life/issues
Classifier: Programming Language :: Python :: 3
Classifier: License :: OSI Approved :: MIT License
Classifier: Operating System :: OS Independent
Requires-Python: >=3.7
License-File: LICENSE
Requires-Dist: importlib_metadata==8.6.1
Requires-Dist: linkify-it-py==2.0.3
Requires-Dist: markdown-it-py==3.0.0
Requires-Dist: mdit-py-plugins==0.4.2
Requires-Dist: mdurl==0.1.2
Requires-Dist: numpy==2.2.4
Requires-Dist: platformdirs==4.3.7
Requires-Dist: Pygments==2.19.1
Requires-Dist: rich==14.0.0
Requires-Dist: textual==3.0.0
Requires-Dist: typing_extensions==4.13.0
Requires-Dist: uc-micro-py==1.0.3
Requires-Dist: zipp==3.21.0
Provides-Extra: test
Requires-Dist: black; extra == "test"
Requires-Dist: pre-commit; extra == "test"
Requires-Dist: mypy; extra == "test"
Requires-Dist: pytest; extra == "test"
Requires-Dist: pytest-cov; extra == "test"
Provides-Extra: deploy
Requires-Dist: build; extra == "deploy"
Requires-Dist: twine; extra == "deploy"
Requires-Dist: setuptools>=61.0; extra == "deploy"
Dynamic: license-file
